{
  "ACTION_INFO" : {
    "IS_TEMP_LOGIN" : "0",
    "MERCHANT_ID" : "0",
    "REAL_NAME" : "yangfan",
    "ROLE_ID" : "20171122161710839073415256267757",
    "SESSIONID" : "f2a313ca96ac732bba5523e63e1fbb9b",
    "USERID" : "20171122163134072944011302057471",
    "USER_NAME" : "yangfan",
    "USER_TYPE" : "1",
    "merUser" : {
      "address" : null,
      "authPassword" : null,
      "cardNumber" : null,
      "cardType" : null,
      "cellPhone" : "13329714137",
      "createTime" : 1511280000000,
      "deptId" : null,
      "eastateId" : null,
      "isRealName" : null,
      "isTempLogin" : false,
      "loginName" : "yangfan",
      "loginPassword" : "e10adc3949ba59abbe56e057f20f883e",
      "merchantId" : "0",
      "needChgPwd" : "1",
      "openFlag" : null,
      "picName" : null,
      "picUrl" : null,
      "position" : "1",
      "pwdExpireDate" : null,
      "realName" : "yangfan",
      "reserveMessage" : null,
      "roleId" : "20171122161710839073415256267757",
      "saleAreaId" : null,
      "sex" : null,
      "status" : "1",
      "tempLoginPassword" : null,
      "tempPwdExpireDate" : null,
      "userCode" : null,
      "userId" : "20171122163134072944011302057471",
      "userType" : "1",
      "webchatNo" : null
    }
  },
  "ACTION_INVOKER" : "",
  "ACTION_NAME" : "merUserApi|merUserLogin",
  "ACTION_RETURN_CODE" : "000000",
  "ACTION_RETURN_MESSAGE" : "修改成功！",
  "ACTION_TOKEN" : {
  "TIMESTAMP" : 1511417441927
  }
}